examples/default.py
examples/example.py
streamlit_chat_prompt/__init__.py
streamlit_chat_prompt/frontend/build/asset-manifest.json
streamlit_chat_prompt/frontend/build/bootstrap.min.css
streamlit_chat_prompt/frontend/build/index.html
streamlit_chat_prompt/frontend/build/static/js/main.a1330c68.js
streamlit_chat_prompt/frontend/build/static/js/main.a1330c68.js.LICENSE.txt
streamlit_chat_prompt/frontend/build/static/js/main.a1330c68.js.map
streamlit_chat_prompt/frontend/node_modules/flatted/python/flatted.py
streamlit_chat_prompt/frontend/node_modules/flatted/python/test.py
streamlit_chat_prompt/frontend/node_modules/node/node_modules/node-linux-x64/share/doc/node/lldb_commands.py
streamlit_chat_prompt-0.4.1.dist-info/licenses/LICENSE
streamlit_chat_prompt-0.4.1.dist-info/METADATA
streamlit_chat_prompt-0.4.1.dist-info/WHEEL
streamlit_chat_prompt-0.4.1.dist-info/top_level.txt
streamlit_chat_prompt-0.4.1.dist-info/RECORD
