Metadata-Version: 2.4
Name: streamlit-chat-prompt
Version: 0.4.1
Summary: A streamlit custom component that allows you to create a chat prompt with paste and image attachment support
Author-email: Tyler House <26489166+tahouse@users.noreply.github.com>
License: Apache-2.0
Keywords: streamlit,component,chat,prompt,paste,image,clipboard,material ui
Classifier: Programming Language :: Python :: 3
Classifier: License :: OSI Approved :: Apache Software License
Classifier: Operating System :: OS Independent
Classifier: Development Status :: 5 - Production/Stable
Classifier: Environment :: Web Environment
Classifier: Intended Audience :: Developers
Classifier: Topic :: Desktop Environment
Classifier: Topic :: Multimedia :: Graphics
Classifier: Topic :: Software Development :: User Interfaces
Requires-Python: >=3.7
License-File: LICENSE
Requires-Dist: streamlit>=0.63
Requires-Dist: pydantic>=2
Provides-Extra: devel
Requires-Dist: wheel; extra == "devel"
Requires-Dist: setuptools==69.0.3; extra == "devel"
Requires-Dist: pytest==7.4.0; extra == "devel"
Requires-Dist: twine~=6.1; extra == "devel"
Requires-Dist: packaging>=24.2; extra == "devel"
Dynamic: license-file
